xarrayfits/__init__.py
xarrayfits/fits.py
xarrayfits/fits_proxy.py
xarrayfits/grid.py
xarrayfits/typing.py
xarrayfits/utils.py
xarray_fits-0.2.5.dist-info/AUTHORS.rst
xarray_fits-0.2.5.dist-info/LICENSE
xarray_fits-0.2.5.dist-info/METADATA
xarray_fits-0.2.5.dist-info/WHEEL
xarray_fits-0.2.5.dist-info/RECORD
